fixedwidthfile/__init__.py
fixedwidthfile/fwf.py
fixedwidthfile-0.84.dist-info/METADATA
fixedwidthfile-0.84.dist-info/WHEEL
fixedwidthfile-0.84.dist-info/licenses/LICENSE
fixedwidthfile-0.84.dist-info/RECORD
