Metadata-Version: 2.4
Name: fixedwidthfile
Version: 0.84
Summary: A package defining functions that assists with managing the data processing for fixed width file
Project-URL: Homepage, https://github.com/andychien009/fixedwidthfile
Project-URL: Issues, https://github.com/andychien009/fixedwidthfile/issues
Author-email: Andy Chien <looking.for.andy.chien@gmail.com>
License-Expression: GPL-3.0
License-File: LICENSE
Classifier: Operating System :: OS Independent
Classifier: Programming Language :: Python :: 3
Requires-Python: >=3.11.0
